ballistic_solver-0.3.3.dist-info/RECORD
ballistic_solver-0.3.3.dist-info/WHEEL
ballistic_solver-0.3.3.dist-info/METADATA
ballistic_solver-0.3.3.dist-info/licenses/LICENSE
ballistic_solver/__init__.py
ballistic_solver/_core.cpython-312-darwin.so
