Metadata-Version: 2.4
Name: ballistic-solver
Version: 0.3.3
Summary: Numerical launch-angle solver for moving targets under gravity and quadratic drag.
License-Expression: MIT
Requires-Python: >=3.10
